<?xml version="1.0" encoding="utf-8" ?><dwsync><file name="appmain.php" local="-4094452865135804416" remote="-4094452861914595032" testing="0" /><file name="country.php" local="-4050293729385250816" remote="-4050293726164041432" testing="0" /><file name="school.php" local="-4094452865135804416" remote="-4094452861914595032" testing="0" /><file name="users.php" local="-4050293729385250816" remote="-4050293726164041432" testing="0" /><file name="certs.php" local="-4050293729385250816" remote="-4050293729385250816" testing="0" /><file name="config.php" local="-4050293729385250816" remote="-4050293729385250816" testing="0" /><file name="county.php" local="-4050293729385250816" remote="-4050293729385250816" testing="0" /><file name="insurance.php" local="-4050293729385250816" remote="-4050293729385250816" testing="0" /><file name="state.php" local="-4050293729385250816" remote="-4050293729385250816" testing="0" /><file name="training.php" local="-4050293729385250816" remote="-4050293729385250816" testing="0" /><file name="welcome.php" local="-4050293729385250816" remote="-4050293729385250816" testing="0" /></dwsync>